fastapi_scaf/__init__.py
fastapi_scaf/__main__.py
fastapi_scaf-1.5.5.dist-info/licenses/LICENSE
fastapi_scaf-1.5.5.dist-info/METADATA
fastapi_scaf-1.5.5.dist-info/WHEEL
fastapi_scaf-1.5.5.dist-info/entry_points.txt
fastapi_scaf-1.5.5.dist-info/top_level.txt
fastapi_scaf-1.5.5.dist-info/RECORD
