Metadata-Version: 2.4
Name: fastapi-scaf
Version: 1.5.5
Summary: upgraded & migrated to fastapi-scaff.
Author-email: axiner <atpuxiner@163.com>
Project-URL: Homepage, https://github.com/atpuxiner/fastapi-scaff
Classifier: Programming Language :: Python :: 3.11
Classifier: Operating System :: OS Independent
Requires-Python: >=3.11
License-File: LICENSE
Requires-Dist: fastapi-scaff
Dynamic: license-file
